<?xml version="1.0" encoding="UTF-8"?>
<suren:autotest xmlns:suren="http://surenpi.com"
	xmlns:xsi="http://www.w3.org/2001/XMLSchema-instance"
	xsi:schemaLocation="http://surenpi.com http://surenpi.com ">
	<suren:engine />
	<suren:pages>
		<suren:page class="com.surenpi.autotest.suite.runner.demo.BaiduHomePage"
			url="https://www.baidu.com/" dataSource="baidu_data">
			<suren:field name="kw" type="input" byId="kw"/>
		</suren:page>
	</suren:pages>
	
	<suren:dataSources>
		<suren:dataSource name="baidu_data" type="xml_data_source" resource="baidu_data.xml"/>
	</suren:dataSources>
</suren:autotest>
